ochoneycomb/__init__.py
ochoneycomb/exporter.py
ochoneycomb-0.0.1.dist-info/LICENSE
ochoneycomb-0.0.1.dist-info/METADATA
ochoneycomb-0.0.1.dist-info/WHEEL
ochoneycomb-0.0.1.dist-info/top_level.txt
ochoneycomb-0.0.1.dist-info/RECORD
