Metadata-Version: 2.1
Name: ochoneycomb
Version: 0.0.1
Summary: OpenCensus exporter for Honeycomb
Home-page: https://github.com/codeboten/opencensus-python-honeycomb-exporter
Author: Alex Boten
Author-email: alrex.boten@gmail.com
License: UNKNOWN
Platform: UNKNOWN
Classifier: Programming Language :: Python :: 3
Classifier: License :: OSI Approved :: Apache Software License
Classifier: Operating System :: OS Independent
Requires-Dist: libhoney
Requires-Dist: opencensus
